augmenta/__init__.py
augmenta/agent.py
augmenta/augmenta.py
augmenta/cli.py
augmenta/cache/__init__.py
augmenta/cache/database.py
augmenta/cache/exceptions.py
augmenta/cache/manager.py
augmenta/cache/models.py
augmenta/cache/process.py
augmenta/config/__init__.py
augmenta/config/get_credentials.py
augmenta/config/read_config.py
augmenta/tools/__init__.py
augmenta/tools/file.py
augmenta/tools/mcp.py
augmenta/tools/search_web.py
augmenta/tools/visit_webpages.py
augmenta/tools/search_providers/__init__.py
augmenta/tools/search_providers/base.py
augmenta/tools/search_providers/brave.py
augmenta/tools/search_providers/brightdata.py
augmenta/tools/search_providers/duckduckgo.py
augmenta/tools/search_providers/google.py
augmenta/tools/search_providers/oxylabs.py
augmenta/utils/get_hash.py
augmenta/utils/limiter.py
augmenta/utils/prompt_formatter.py
augmenta/utils/validators.py
augmenta-0.1.2.dist-info/licenses/LICENSE
augmenta-0.1.2.dist-info/METADATA
augmenta-0.1.2.dist-info/WHEEL
augmenta-0.1.2.dist-info/entry_points.txt
augmenta-0.1.2.dist-info/top_level.txt
augmenta-0.1.2.dist-info/RECORD
