Metadata-Version: 2.4
Name: augmenta
Version: 0.1.2
Summary: AI-powered library for data enrichment using search results
Author: Nicu Calcea
License: Apache-2.0
Project-URL: Homepage, https://github.com/Global-Witness/augmenta
Project-URL: Changelog, https://github.com/Global-Witness/augmenta/releases
Project-URL: Issues, https://github.com/Global-Witness/augmenta/issues
Project-URL: CI, https://github.com/Global-Witness/augmenta/actions
Classifier: License :: OSI Approved :: Apache Software License
Requires-Python: >=3.10
License-File: LICENSE
Requires-Dist: click>=8.0.0
Requires-Dist: python-dotenv>=1.0.0
Requires-Dist: pyyaml>=6.0.0
Requires-Dist: pandas>=1.0.0
Requires-Dist: pydantic>=2.0.0
Requires-Dist: pydantic-ai>=0.6.0
Requires-Dist: logfire[httpx]>=3.9.0
Requires-Dist: trafilatura>=2.0.0
Requires-Dist: aiolimiter>=1.2.0
Requires-Dist: tenacity<9.0.0,>=8.2.3
Provides-Extra: test
Requires-Dist: pytest; extra == "test"
Provides-Extra: logfire
Requires-Dist: pydantic-ai[logfire]; extra == "logfire"
Dynamic: license-file
